roku_dev_cli/__init__.py
roku_dev_cli/roku_dev_cli.py
roku_dev_cli/version.py
roku_dev_cli/reports/index.html
roku_dev_cli-0.37.1.dist-info/DESCRIPTION.rst
roku_dev_cli-0.37.1.dist-info/METADATA
roku_dev_cli-0.37.1.dist-info/RECORD
roku_dev_cli-0.37.1.dist-info/WHEEL
roku_dev_cli-0.37.1.dist-info/entry_points.txt
roku_dev_cli-0.37.1.dist-info/metadata.json
roku_dev_cli-0.37.1.dist-info/top_level.txt
