Metadata-Version: 2.0
Name: roku-dev-cli
Version: 0.37.1
Summary: Roku Command-Line Tool
Home-page: https://github.com/hulu/roku-dev-cli
Author: Josh Stratton
Author-email: josh.stratton@hulu.com
License: UNKNOWN
Platform: UNKNOWN
Requires-Dist: beautifulsoup4
Requires-Dist: graphviz
Requires-Dist: ipaddress
Requires-Dist: requests
